LICENSE
README.md
setup.cfg
setup.py
commandnotfound/__init__.py
commandnotfound.egg-info/PKG-INFO
commandnotfound.egg-info/SOURCES.txt
commandnotfound.egg-info/dependency_links.txt
commandnotfound.egg-info/top_level.txt
tests/__init__.py
tests/test_report_func.py
tests/test_wrap_func.py