Metadata-Version: 2.1
Name: commandnotfound
Version: 0.5.0
Summary: A wrapper of command-not-found command for subprocess.run
Home-page: https://github.com/tos-kamiya/commandnotfound
Author: Toshihiro kamiya
Author-email: kamiya@mbj.nifty.com
License: Public Domain
Classifier: Topic :: System :: System Shells
Classifier: Programming Language :: Python :: 3.8
Classifier: Operating System :: POSIX :: Linux
Classifier: License :: Public Domain
Classifier: Development Status :: 3 - Alpha
Requires-Python: >=3.8
License-File: LICENSE
